{
  "tasks": {
    "dev": "deno run -A --node-modules-dir npm:vite",
    "build": "deno run -A --node-modules-dir npm:vite build",
    "preview": "deno run -A --node-modules-dir npm:vite preview",
    "serve": "deno run --allow-net --allow-read jsr:@std/http@1/file-server dist/"
  },
  "compilerOptions": {
    "lib": ["ES2020", "DOM", "DOM.Iterable"],
    "jsx": "react-jsx",
    "jsxImportSource": "react",
    "jsxImportSourceTypes": "@types/react"
  },
  "imports": {
    "@deno/vite-plugin": "npm:@deno/vite-plugin@^1.0.0",
    "@types/react": "npm:@types/react@^18.3.1",
    "@types/react-dom": "npm:@types/react-dom@^18.3.1",
    "@vitejs/plugin-react": "npm:@vitejs/plugin-react@^4.3.2",
    "react": "npm:react@^18.3.1",
    "react-dom": "npm:react-dom@^18.3.1",
    "vite": "npm:vite@^5.4.8"
  }
}
